{
 "results": [
  {
   "searchTerm": "pub(the daily beast) AND (\"Luther Strange\")  AND pd(20170101-20171231)",
   "numberofResults": "53 results"
  },
  {
   "searchTerm": "pub(the daily beast) AND (\"Patrick Leahy\")  AND pd(20170101-20171231)",
   "numberofResults": "14 results"
  },
  {
   "searchTerm": "pub(the daily beast) AND (\"Orrin Hatch\")  AND pd(20170101-20171231)",
   "numberofResults": "36 results"
  },
  {
   "searchTerm": "pub(the daily beast) AND (\"Thad Cochran\")  AND pd(20170101-20171231)",
   "numberofResults": "2 results"
  },
  {
   "searchTerm": "pub(the daily beast) AND (\"Charles Grassley\")  AND pd(20170101-20171231)",
   "numberofResults": "6 results"
  },
  {
   "searchTerm": "pub(the daily beast) AND (\"Mitch McConnell\")  AND pd(20170101-20171231)",
   "numberofResults": "221 results"
  },
  {
   "searchTerm": "pub(the daily beast) AND (\"Richard Shelby\")  AND pd(20170101-20171231)",
   "numberofResults": "24 results"
  },
  {
   "searchTerm": "pub(the daily beast) AND (\"John McCain\")  AND pd(20170101-20171231)",
   "numberofResults": "189 results"
  },
  {
   "searchTerm": "pub(the daily beast) AND (\"Dianne Feinstein\")  AND pd(20170101-20171231)",
   "numberofResults": "44 results"
  },
  {
   "searchTerm": "pub(the daily beast) AND (\"Patty Murray\")  AND pd(20170101-20171231)",
   "numberofResults": "27 results"
  },
  {
   "searchTerm": "pub(the daily beast) AND (\"Jim Inhofe\")  AND pd(20170101-20171231)",
   "numberofResults": "4 results"
  },
  {
   "searchTerm": "pub(the daily beast) AND (\"Ron Wyden\")  AND pd(20170101-20171231)",
   "numberofResults": "26 results"
  },
  {
   "searchTerm": "pub(the daily beast) AND (\"Pat Roberts\")  AND pd(20170101-20171231)",
   "numberofResults": "8 results"
  },
  {
   "searchTerm": "pub(the daily beast) AND (\"Richard Durbin\")  AND pd(20170101-20171231)",
   "numberofResults": "3 results"
  },
  {
   "searchTerm": "pub(the daily beast) AND (\"Jack Reed\")  AND pd(20170101-20171231)",
   "numberofResults": "3 results"
  },
  {
   "searchTerm": "pub(the daily beast) AND (\"Jeff Sessions\")  AND pd(20170101-20171231)",
   "numberofResults": "328 results"
  },
  {
   "searchTerm": "pub(the daily beast) AND (\"Susan Collins\")  AND pd(20170101-20171231)",
   "numberofResults": "65 results"
  },
  {
   "searchTerm": "pub(the daily beast) AND (\"Mike Enzi\")  AND pd(20170101-20171231)",
   "numberofResults": "1 result"
  },
  {
   "searchTerm": "pub(the daily beast) AND (\"Charles Schumer\")  AND pd(20170101-20171231)",
   "numberofResults": "8 results"
  },
  {
   "searchTerm": "pub(the daily beast) AND (\"Mike Crapo\")  AND pd(20170101-20171231)"
  },
  {
   "searchTerm": "pub(the daily beast) AND (\"Bill Nelson\")  AND pd(20170101-20171231)",
   "numberofResults": "5 results"
  },
  {
   "searchTerm": "pub(the daily beast) AND (\"Tom Carper\")  AND pd(20170101-20171231)",
   "numberofResults": "10 results"
  },
  {
   "searchTerm": "pub(the daily beast) AND (\"Debbie Stabenow\")  AND pd(20170101-20171231)",
   "numberofResults": "4 results"
  },
  {
   "searchTerm": "pub(the daily beast) AND (\"Maria Cantwell\")  AND pd(20170101-20171231)",
   "numberofResults": "1 result"
  },
  {
   "searchTerm": "pub(the daily beast) AND (\"John Cornyn\")  AND pd(20170101-20171231)",
   "numberofResults": "27 results"
  },
  {
   "searchTerm": "pub(the daily beast) AND (\"Lisa Murkowski\")  AND pd(20170101-20171231)",
   "numberofResults": "38 results"
  },
  {
   "searchTerm": "pub(the daily beast) AND (\"Lindsey Graham\")  AND pd(20170101-20171231)",
   "numberofResults": "99 results"
  },
  {
   "searchTerm": "pub(the daily beast) AND (\"Lamar Alexander\")  AND pd(20170101-20171231)",
   "numberofResults": "23 results"
  },
  {
   "searchTerm": "pub(the daily beast) AND (\"Richard Burr\")  AND pd(20170101-20171231)",
   "numberofResults": "42 results"
  },
  {
   "searchTerm": "pub(the daily beast) AND (\"John Thune\")  AND pd(20170101-20171231)",
   "numberofResults": "17 results"
  },
  {
   "searchTerm": "pub(the daily beast) AND (\"Johnny Isakson\")  AND pd(20170101-20171231)",
   "numberofResults": "5 results"
  },
  {
   "searchTerm": "pub(the daily beast) AND (\"Robert Menendez\")  AND pd(20170101-20171231)"
  },
  {
   "searchTerm": "pub(the daily beast) AND (\"Ben Cardin\")  AND pd(20170101-20171231)",
   "numberofResults": "21 results"
  },
  {
   "searchTerm": "pub(the daily beast) AND (\"Bernie Sanders\")  AND pd(20170101-20171231)",
   "numberofResults": "156 results"
  },
  {
   "searchTerm": "pub(the daily beast) AND (\"Sherrod Brown\")  AND pd(20170101-20171231)",
   "numberofResults": "13 results"
  },
  {
   "searchTerm": "pub(the daily beast) AND (\"Bob Casey\")  AND pd(20170101-20171231)",
   "numberofResults": "5 results"
  },
  {
   "searchTerm": "pub(the daily beast) AND (\"Bob Corker\")  AND pd(20170101-20171231)",
   "numberofResults": "73 results"
  },
  {
   "searchTerm": "pub(the daily beast) AND (\"Claire McCaskill\")  AND pd(20170101-20171231)",
   "numberofResults": "21 results"
  },
  {
   "searchTerm": "pub(the daily beast) AND (\"Amy Klobuchar\")  AND pd(20170101-20171231)",
   "numberofResults": "10 results"
  },
  {
   "searchTerm": "pub(the daily beast) AND (\"Sheldon Whitehouse\")  AND pd(20170101-20171231)",
   "numberofResults": "12 results"
  },
  {
   "searchTerm": "pub(the daily beast) AND (\"Jon Tester\")  AND pd(20170101-20171231)",
   "numberofResults": "4 results"
  },
  {
   "searchTerm": "pub(the daily beast) AND (\"John Barrasso\")  AND pd(20170101-20171231)",
   "numberofResults": "5 results"
  },
  {
   "searchTerm": "pub(the daily beast) AND (\"Roger Wicker\")  AND pd(20170101-20171231)",
   "numberofResults": "5 results"
  },
  {
   "searchTerm": "pub(the daily beast) AND (\"Tom Udall\")  AND pd(20170101-20171231)",
   "numberofResults": "2 results"
  },
  {
   "searchTerm": "pub(the daily beast) AND (\"Jeanne Shaheen\")  AND pd(20170101-20171231)",
   "numberofResults": "6 results"
  },
  {
   "searchTerm": "pub(the daily beast) AND (\"Mark Warner\")  AND pd(20170101-20171231)",
   "numberofResults": "58 results"
  },
  {
   "searchTerm": "pub(the daily beast) AND (\"James Risch\")  AND pd(20170101-20171231)",
   "numberofResults": "1 result"
  },
  {
   "searchTerm": "pub(the daily beast) AND (\"Jeff Merkley\")  AND pd(20170101-20171231)",
   "numberofResults": "4 results"
  },
  {
   "searchTerm": "pub(the daily beast) AND (\"Michael Bennet\")  AND pd(20170101-20171231)",
   "numberofResults": "1 result"
  },
  {
   "searchTerm": "pub(the daily beast) AND (\"Kirsten Gillibrand\")  AND pd(20170101-20171231)",
   "numberofResults": "29 results"
  },
  {
   "searchTerm": "pub(the daily beast) AND (\"Al Franken\")  AND pd(20170101-20171231)",
   "numberofResults": "104 results"
  },
  {
   "searchTerm": "pub(the daily beast) AND (\"Joe Manchin\")  AND pd(20170101-20171231)",
   "numberofResults": "19 results"
  },
  {
   "searchTerm": "pub(the daily beast) AND (\"Chris Coons\")  AND pd(20170101-20171231)",
   "numberofResults": "13 results"
  },
  {
   "searchTerm": "pub(the daily beast) AND (\"Roy Blunt\")  AND pd(20170101-20171231)",
   "numberofResults": "10 results"
  },
  {
   "searchTerm": "pub(the daily beast) AND (\"Jerry Moran\")  AND pd(20170101-20171231)",
   "numberofResults": "7 results"
  },
  {
   "searchTerm": "pub(the daily beast) AND (\"Rob Portman\")  AND pd(20170101-20171231)",
   "numberofResults": "25 results"
  },
  {
   "searchTerm": "pub(the daily beast) AND (\"John Boozman\")  AND pd(20170101-20171231)"
  },
  {
   "searchTerm": "pub(the daily beast) AND (\"Pat Toomey\")  AND pd(20170101-20171231)",
   "numberofResults": "8 results"
  },
  {
   "searchTerm": "pub(the daily beast) AND (\"John Hoeven\")  AND pd(20170101-20171231)",
   "numberofResults": "2 results"
  },
  {
   "searchTerm": "pub(the daily beast) AND (\"Marco Rubio\")  AND pd(20170101-20171231)",
   "numberofResults": "72 results"
  },
  {
   "searchTerm": "pub(the daily beast) AND (\"Ron Johnson\")  AND pd(20170101-20171231)",
   "numberofResults": "20 results"
  },
  {
   "searchTerm": "pub(the daily beast) AND (\"Rand Paul\")  AND pd(20170101-20171231)",
   "numberofResults": "71 results"
  },
  {
   "searchTerm": "pub(the daily beast) AND (\"Richard Blumenthal\")  AND pd(20170101-20171231)",
   "numberofResults": "14 results"
  },
  {
   "searchTerm": "pub(the daily beast) AND (\"Mike Lee\")  AND pd(20170101-20171231)",
   "numberofResults": "22 results"
  },
  {
   "searchTerm": "pub(the daily beast) AND (\"Dean Heller\")  AND pd(20170101-20171231)",
   "numberofResults": "22 results"
  },
  {
   "searchTerm": "pub(the daily beast) AND (\"Brian Schatz\")  AND pd(20170101-20171231)",
   "numberofResults": "10 results"
  },
  {
   "searchTerm": "pub(the daily beast) AND (\"Tim Scott\")  AND pd(20170101-20171231)",
   "numberofResults": "4 results"
  },
  {
   "searchTerm": "pub(the daily beast) AND (\"Tammy Baldwin\")  AND pd(20170101-20171231)",
   "numberofResults": "9 results"
  },
  {
   "searchTerm": "pub(the daily beast) AND (\"Jeff Flake\")  AND pd(20170101-20171231)",
   "numberofResults": "76 results"
  },
  {
   "searchTerm": "pub(the daily beast) AND (\"Joe Donnelly\")  AND pd(20170101-20171231)",
   "numberofResults": "8 results"
  },
  {
   "searchTerm": "pub(the daily beast) AND (\"Chris Murphy\")  AND pd(20170101-20171231)",
   "numberofResults": "18 results"
  },
  {
   "searchTerm": "pub(the daily beast) AND (\"Mazie Hirono\")  AND pd(20170101-20171231)",
   "numberofResults": "8 results"
  },
  {
   "searchTerm": "pub(the daily beast) AND (\"Martin Heinrich\")  AND pd(20170101-20171231)",
   "numberofResults": "7 results"
  },
  {
   "searchTerm": "pub(the daily beast) AND (\"Angus King\")  AND pd(20170101-20171231)",
   "numberofResults": "18 results"
  },
  {
   "searchTerm": "pub(the daily beast) AND (\"Tim Kaine\")  AND pd(20170101-20171231)",
   "numberofResults": "23 results"
  },
  {
   "searchTerm": "pub(the daily beast) AND (\"Ted Cruz\")  AND pd(20170101-20171231)",
   "numberofResults": "112 results"
  },
  {
   "searchTerm": "pub(the daily beast) AND (\"Elizabeth Warren\")  AND pd(20170101-20171231)",
   "numberofResults": "62 results"
  },
  {
   "searchTerm": "pub(the daily beast) AND (\"Deb Fischer\")  AND pd(20170101-20171231)",
   "numberofResults": "2 results"
  },
  {
   "searchTerm": "pub(the daily beast) AND (\"Heidi Heitkamp\")  AND pd(20170101-20171231)",
   "numberofResults": "11 results"
  },
  {
   "searchTerm": "pub(the daily beast) AND (\"Edward Markey\")  AND pd(20170101-20171231)",
   "numberofResults": "1 result"
  },
  {
   "searchTerm": "pub(the daily beast) AND (\"Cory Booker\")  AND pd(20170101-20171231)",
   "numberofResults": "27 results"
  },
  {
   "searchTerm": "pub(the daily beast) AND (\"Shelley Moore Capito\")  AND pd(20170101-20171231)",
   "numberofResults": "12 results"
  },
  {
   "searchTerm": "pub(the daily beast) AND (\"Gary Peters\")  AND pd(20170101-20171231)"
  },
  {
   "searchTerm": "pub(the daily beast) AND (\"Bill Cassidy\")  AND pd(20170101-20171231)",
   "numberofResults": "36 results"
  },
  {
   "searchTerm": "pub(the daily beast) AND (\"Cory Gardner\")  AND pd(20170101-20171231)",
   "numberofResults": "26 results"
  },
  {
   "searchTerm": "pub(the daily beast) AND (\"James Lankford\")  AND pd(20170101-20171231)",
   "numberofResults": "10 results"
  },
  {
   "searchTerm": "pub(the daily beast) AND (\"Tom Cotton\")  AND pd(20170101-20171231)",
   "numberofResults": "20 results"
  },
  {
   "searchTerm": "pub(the daily beast) AND (\"Steve Daines\")  AND pd(20170101-20171231)",
   "numberofResults": "5 results"
  },
  {
   "searchTerm": "pub(the daily beast) AND (\"Mike Rounds\")  AND pd(20170101-20171231)",
   "numberofResults": "10 results"
  },
  {
   "searchTerm": "pub(the daily beast) AND (\"David Perdue\")  AND pd(20170101-20171231)",
   "numberofResults": "4 results"
  },
  {
   "searchTerm": "pub(the daily beast) AND (\"Thom Tillis\")  AND pd(20170101-20171231)",
   "numberofResults": "11 results"
  },
  {
   "searchTerm": "pub(the daily beast) AND (\"Joni Ernst\")  AND pd(20170101-20171231)",
   "numberofResults": "5 results"
  },
  {
   "searchTerm": "pub(the daily beast) AND (\"Ben Sasse\")  AND pd(20170101-20171231)",
   "numberofResults": "18 results"
  },
  {
   "searchTerm": "pub(the daily beast) AND (\"Dan Sullivan\")  AND pd(20170101-20171231)",
   "numberofResults": "1 result"
  },
  {
   "searchTerm": "pub(the daily beast) AND (\"Chris Van Hollen\")  AND pd(20170101-20171231)",
   "numberofResults": "6 results"
  },
  {
   "searchTerm": "pub(the daily beast) AND (\"Todd Young\")  AND pd(20170101-20171231)",
   "numberofResults": "3 results"
  },
  {
   "searchTerm": "pub(the daily beast) AND (\"Tammy Duckworth\")  AND pd(20170101-20171231)",
   "numberofResults": "3 results"
  },
  {
   "searchTerm": "pub(the daily beast) AND (\"Maggie Hassan\")  AND pd(20170101-20171231)",
   "numberofResults": "8 results"
  },
  {
   "searchTerm": "pub(the daily beast) AND (\"Kamala Harris\")  AND pd(20170101-20171231)",
   "numberofResults": "29 results"
  },
  {
   "searchTerm": "pub(the daily beast) AND (\"John Neely Kennedy\")  AND pd(20170101-20171231)",
   "numberofResults": "1 result"
  },
  {
   "searchTerm": "pub(the daily beast) AND (\"Catherine Cortez Masto\")  AND pd(20170101-20171231)"
  }
 ]
}